gcp_devrel/__init__.py
gcp_devrel/testing/__init__.py
gcp_devrel/testing/appengine.py
gcp_devrel/testing/eventually_consistent.py
gcp_devrel/testing/eventually_consistent_test.py
gcp_devrel/testing/flaky.py
gcp_devrel/testing/requirements_test.py
gcp_devrel/tools/__init__.py
gcp_devrel/tools/appengine.py
gcp_devrel/tools/pylint.py
gcp_devrel/tools/requirements.py
gcp_devrel_py_tools-0.0.16.dist-info/LICENSE
gcp_devrel_py_tools-0.0.16.dist-info/METADATA
gcp_devrel_py_tools-0.0.16.dist-info/WHEEL
gcp_devrel_py_tools-0.0.16.dist-info/entry_points.txt
gcp_devrel_py_tools-0.0.16.dist-info/top_level.txt
gcp_devrel_py_tools-0.0.16.dist-info/RECORD
