Metadata-Version: 2.1
Name: gcp-devrel-py-tools
Version: 0.0.16
Summary: Tools for Cloud Platform Python libraries and samples.
Home-page: https://github.com/GoogleCloudPlatform/python-repo-tools
Author: Thea Flowers
Author-email: theaflowers@google.com
License: Apache Software License
Platform: UNKNOWN
Classifier: Operating System :: POSIX
Requires-Dist: google-cloud-core
Requires-Dist: requests
Requires-Dist: retrying
Requires-Dist: setuptools (>=25.0.0)
Requires-Dist: packaging
Requires-Dist: pylint (>=1.8.0)
